{
  "resourceType": "ValueSet",
  "id": "AllergicContactDermatitisOfEyelidConditions",
  "url": "<FHIR-server>/ValueSet/AllergicContactDermatitisOfEyelidConditions",
  "identifier": [
    {
      "system": "urn:ietf:rfc:3986",
      "value": "urn:oid:AllergicContactDermatitisOfEyelidConditions"
    }
  ],
  "version": "Latest",
  "name": "Allergic contact dermatitis of eyelid Condition",
  "title": "Allergic contact dermatitis of eyelid Condition",
  "status": "active",
  "publisher": "CMS",
  "compose": {
    "include": [
      {
        "system": "http://snomed.info/sct",
        "concept": [
          {
            "code": "402249007",
            "display": "Allergic contact dermatitis of eyelid (disorder)"
          }
        ]
      }
    ]
  }
}
